spacer/__init__.py
spacer/_version.py
spacer/handlers.py
spacer/tests/__init__.py
spacer/tests/test_handlers.py
spacer-0.0.2.data/data/etc/jupyter/jupyter_notebook_config.d/spacer.json
spacer-0.0.2.data/data/etc/jupyter/jupyter_server_config.d/spacer.json
spacer-0.0.2.data/data/share/jupyter/labextensions/@datalayer/spacer/build_log.json
spacer-0.0.2.data/data/share/jupyter/labextensions/@datalayer/spacer/package.json
spacer-0.0.2.data/data/share/jupyter/labextensions/@datalayer/spacer/schemas/@datalayer/spacer/package.json.orig
spacer-0.0.2.data/data/share/jupyter/labextensions/@datalayer/spacer/schemas/@datalayer/spacer/plugin.json
spacer-0.0.2.data/data/share/jupyter/labextensions/@datalayer/spacer/static/lib_index_js-webpack_sharing_consume_default_react-dom-webpack_sharing_consume_default_styled-bda8b9.7036043c9ab750a2c267.js
spacer-0.0.2.data/data/share/jupyter/labextensions/@datalayer/spacer/static/lib_index_js-webpack_sharing_consume_default_react-dom-webpack_sharing_consume_default_styled-bda8b9.7036043c9ab750a2c267.js.map
spacer-0.0.2.data/data/share/jupyter/labextensions/@datalayer/spacer/static/remoteEntry.f7e0d309e158e2fd8c03.js
spacer-0.0.2.data/data/share/jupyter/labextensions/@datalayer/spacer/static/remoteEntry.f7e0d309e158e2fd8c03.js.map
spacer-0.0.2.data/data/share/jupyter/labextensions/@datalayer/spacer/static/style.js
spacer-0.0.2.data/data/share/jupyter/labextensions/@datalayer/spacer/static/style_index_js.ede798e58282f34ecea6.js
spacer-0.0.2.data/data/share/jupyter/labextensions/@datalayer/spacer/static/style_index_js.ede798e58282f34ecea6.js.map
spacer-0.0.2.data/data/share/jupyter/labextensions/@datalayer/spacer/static/vendors-node_modules_css-loader_dist_runtime_api_js-node_modules_css-loader_dist_runtime_cssW-72eba1.9c65c0354ff9f20e568b.js
spacer-0.0.2.dist-info/METADATA
spacer-0.0.2.dist-info/WHEEL
spacer-0.0.2.dist-info/licenses/LICENSE
spacer-0.0.2.dist-info/RECORD
